{
      "apps": [
		{
			"name": "dsocial",
		  "script" : "./bin/www",
		  "env": {
		          "NODE_ENV": "production",
		          "PORT": "8080",
		          "DBASE": "dsocial",
		          "SERVER": "https://dsocial.brown.gob.ar",
		          "FAVICON": "favicon.ico",
		          "PUBLIC": "/www/dsocial"
		  }
		},

		{
			"name": "salud",
		  "script" : "./bin/www",
		  "env": {
		          "NODE_ENV": "production",
		          "PORT": "8081",
		          "DBASE": "salud",
		          "SERVER": "https://salud.brown.gob.ar",
		          "FAVICON": "favicon.ico",
		          "PUBLIC": "/www/salud"
		  }
		}

	]
}
